aisentry/__init__.py
aisentry/cli.py
aisentry/config.py
aisentry/fp_reducer.py
aisentry/audit/__init__.py
aisentry/audit/engine.py
aisentry/audit/models.py
aisentry/audit/analyzers/__init__.py
aisentry/audit/analyzers/ast_analyzer.py
aisentry/audit/analyzers/config_analyzer.py
aisentry/audit/analyzers/dependency_analyzer.py
aisentry/audit/controls/__init__.py
aisentry/audit/controls/base_control.py
aisentry/audit/controls/blue_team.py
aisentry/audit/controls/data_privacy.py
aisentry/audit/controls/ethical_ai.py
aisentry/audit/controls/governance.py
aisentry/audit/controls/hallucination.py
aisentry/audit/controls/incident_response.py
aisentry/audit/controls/model_security.py
aisentry/audit/controls/owasp_llm.py
aisentry/audit/controls/prompt_security.py
aisentry/audit/controls/supply_chain.py
aisentry/audit/reports/__init__.py
aisentry/audit/reports/html_reporter.py
aisentry/audit/reports/json_reporter.py
aisentry/audit/scoring/__init__.py
aisentry/audit/scoring/maturity_scorer.py
aisentry/core/__init__.py
aisentry/core/scanner.py
aisentry/core/tester.py
aisentry/evaluation/__init__.py
aisentry/evaluation/benchmark_runner.py
aisentry/evaluation/metrics.py
aisentry/live_detectors/__init__.py
aisentry/live_detectors/adversarial_inputs.py
aisentry/live_detectors/base_live_detector.py
aisentry/live_detectors/behavioral_anomaly.py
aisentry/live_detectors/bias.py
aisentry/live_detectors/data_leakage.py
aisentry/live_detectors/dos.py
aisentry/live_detectors/hallucination.py
aisentry/live_detectors/jailbreak.py
aisentry/live_detectors/model_extraction.py
aisentry/live_detectors/output_manipulation.py
aisentry/live_detectors/prompt_injection.py
aisentry/live_detectors/supply_chain.py
aisentry/ml/__init__.py
aisentry/ml/feature_extractor.py
aisentry/ml/model_inference.py
aisentry/ml/models/prompt_injection_v1.pkl
aisentry/ml/training/__init__.py
aisentry/ml/training/export_onnx.py
aisentry/ml/training/synthetic_generator.py
aisentry/ml/training/trainer.py
aisentry-1.0.0.dist-info/licenses/LICENSE
aisentry-1.0.0.dist-info/METADATA
aisentry-1.0.0.dist-info/WHEEL
aisentry-1.0.0.dist-info/entry_points.txt
aisentry-1.0.0.dist-info/top_level.txt
aisentry-1.0.0.dist-info/RECORD
