Metadata-Version: 2.4
Name: aisentry
Version: 1.0.0
Summary: AI Sentry - Unified AI/LLM Security Scanner for Static Code Analysis + Live Model Testing
Author: AISentry Team
License: MIT
Project-URL: Homepage, https://aisentry.co
Project-URL: Repository, https://github.com/deosha/aisentry
Project-URL: Documentation, https://aisentry.co/docs.html
Project-URL: Issues, https://github.com/deosha/aisentry/issues
Keywords: security,llm,ai,owasp,static-analysis,live-testing,vulnerability-scanner,aisentry
Classifier: Development Status :: 4 - Beta
Classifier: Intended Audience :: Developers
Classifier: Topic :: Security
Classifier: License :: OSI Approved :: MIT License
Classifier: Programming Language :: Python :: 3.8
Classifier: Programming Language :: Python :: 3.9
Classifier: Programming Language :: Python :: 3.10
Classifier: Programming Language :: Python :: 3.11
Classifier: Programming Language :: Python :: 3.12
Classifier: Programming Language :: Python :: 3.13
Requires-Python: >=3.8
License-File: LICENSE
Requires-Dist: click>=8.0.0
Requires-Dist: rich>=13.0.0
Requires-Dist: pyyaml>=6.0.0
Requires-Dist: aiohttp>=3.8.0
Requires-Dist: httpx>=0.24.0
Requires-Dist: openai>=1.0.0
Requires-Dist: anthropic>=0.8.0
Requires-Dist: numpy>=1.21.0
Requires-Dist: scipy>=1.7.0
Requires-Dist: detect-secrets>=1.4.0
Requires-Dist: astunparse>=1.6.3; python_version < "3.9"
Requires-Dist: typing-extensions>=4.0.0; python_version < "3.10"
Provides-Extra: bedrock
Requires-Dist: boto3>=1.28.0; extra == "bedrock"
Provides-Extra: vertex
Requires-Dist: google-cloud-aiplatform>=1.25.0; extra == "vertex"
Requires-Dist: google-auth>=2.0.0; extra == "vertex"
Provides-Extra: azure
Requires-Dist: azure-identity>=1.12.0; extra == "azure"
Provides-Extra: ml
Requires-Dist: scikit-learn>=1.0.0; extra == "ml"
Provides-Extra: cloud
Requires-Dist: boto3>=1.28.0; extra == "cloud"
Requires-Dist: google-cloud-aiplatform>=1.25.0; extra == "cloud"
Requires-Dist: google-auth>=2.0.0; extra == "cloud"
Requires-Dist: azure-identity>=1.12.0; extra == "cloud"
Provides-Extra: dev
Requires-Dist: pytest>=7.0.0; extra == "dev"
Requires-Dist: pytest-cov>=4.0.0; extra == "dev"
Requires-Dist: pytest-asyncio>=0.21.0; extra == "dev"
Requires-Dist: black>=23.0.0; extra == "dev"
Requires-Dist: ruff>=0.1.0; extra == "dev"
Requires-Dist: mypy>=1.0.0; extra == "dev"
Requires-Dist: types-pyyaml>=6.0.0; extra == "dev"
Provides-Extra: all
Requires-Dist: boto3>=1.28.0; extra == "all"
Requires-Dist: google-cloud-aiplatform>=1.25.0; extra == "all"
Requires-Dist: google-auth>=2.0.0; extra == "all"
Requires-Dist: azure-identity>=1.12.0; extra == "all"
Requires-Dist: scikit-learn>=1.0.0; extra == "all"
Requires-Dist: pytest>=7.0.0; extra == "all"
Requires-Dist: pytest-cov>=4.0.0; extra == "all"
Requires-Dist: pytest-asyncio>=0.21.0; extra == "all"
Requires-Dist: black>=23.0.0; extra == "all"
Requires-Dist: ruff>=0.1.0; extra == "all"
Requires-Dist: mypy>=1.0.0; extra == "all"
Requires-Dist: types-pyyaml>=6.0.0; extra == "all"
Dynamic: license-file
